pyppr/__init__.py
pyppr/_pyppr.py
tests/__init__.py
tests/test_pyppr.py
pyppr-0.1.1.dist-info/LICENSE.txt
pyppr-0.1.1.dist-info/METADATA
pyppr-0.1.1.dist-info/WHEEL
pyppr-0.1.1.dist-info/top_level.txt
pyppr-0.1.1.dist-info/RECORD
